[
    {
        "url": "https://raw.githubusercontent.com/ctnkyaumt/cstr-sp/builds/cstrsp.cs3",
        "status": 1,
        "version": 1,
        "name": "cstrsp",
        "internalName": "cstrsp",
        "authors": [
            "cstrsp"
        ],
        "description": "strmd.link parser extension",
        "fileSize": 30639,
        "repositoryUrl": "https://github.com/ctnkyaumt/cstr-sp",
        "language": "en",
        "tvTypes": [
            "Live"
        ],
        "apiVersion": 1,
        "fileHash": "sha256-446d4b9c739a0929745b598a0a8d0782e058f2888f7838a0cbbd127b664e842c"
    }
]