[
    {
        "url": "https://raw.githubusercontent.com/ctnkyaumt/cstr-sp/builds/cstrsp.cs3",
        "status": 1,
        "version": 7,
        "name": "cstrsp",
        "internalName": "cstrsp",
        "authors": [
            "cstrsp"
        ],
        "description": "strmd.link parser extension",
        "fileSize": 92759,
        "repositoryUrl": "https://github.com/ctnkyaumt/cstr-sp",
        "language": "en",
        "tvTypes": [
            "Live"
        ],
        "apiVersion": 1,
        "fileHash": "sha256-ce83dc71554655e27c002062e721429774be29d44f088f1876ad41e3985f32b5"
    }
]